odoo9_addon_medical_medicament-9.0.1.0.0-py2.7-nspkg.pth
odoo_addons/medical_medicament/__openerp__.py
odoo_addons/medical_medicament/__init__.py
odoo_addons/medical_medicament/README.rst
odoo_addons/medical_medicament/security/ir.model.access.csv
odoo_addons/medical_medicament/models/product_template.py
odoo_addons/medical_medicament/models/medical_medicament.py
odoo_addons/medical_medicament/models/medical_drug_route.py
odoo_addons/medical_medicament/models/__init__.py
odoo_addons/medical_medicament/models/medical_drug_form.py
odoo_addons/medical_medicament/views/product_product_view.xml
odoo_addons/medical_medicament/views/medical_drug_form_view.xml
odoo_addons/medical_medicament/views/medical_menu.xml
odoo_addons/medical_medicament/views/medical_medicament_view.xml
odoo_addons/medical_medicament/views/medical_drug_route_view.xml
odoo_addons/medical_medicament/data/medical_drug_form.xml
odoo_addons/medical_medicament/data/medical_drug_route.xml
odoo_addons/medical_medicament/tests/test_medical_drug_route.py
odoo_addons/medical_medicament/tests/__init__.py
odoo_addons/medical_medicament/tests/test_medical_drug_form.py
odoo_addons/medical_medicament/tests/test_medical_medicament.py
odoo_addons/medical_medicament/demo/medical_medicament_demo.xml
odoo_addons/medical_medicament/static/description/icon.png
odoo9_addon_medical_medicament-9.0.1.0.0.dist-info/top_level.txt
odoo9_addon_medical_medicament-9.0.1.0.0.dist-info/WHEEL
odoo9_addon_medical_medicament-9.0.1.0.0.dist-info/RECORD
odoo9_addon_medical_medicament-9.0.1.0.0.dist-info/metadata.json
odoo9_addon_medical_medicament-9.0.1.0.0.dist-info/DESCRIPTION.rst
odoo9_addon_medical_medicament-9.0.1.0.0.dist-info/METADATA
odoo9_addon_medical_medicament-9.0.1.0.0.dist-info/namespace_packages.txt
